[
  {"model":"patients.patient","pk":1,"fields":{"patient_id":"201810750","name":"Timothy Garcia","sex":1,"age":66.0,"status":"Alive","operation_date":"2018-01-02","hospitalization_number":"1338898","diagnosis_pathological":1,"diagnosis_etiological":3,"diagnosis_coexisting":4,"bmi":22.53,"meld_score":2.4,"child_pugh_score":8,"child_pugh_category":"B","cold_ischemia_time":367,"warm_ischemia_time":5,"operative_time":585,"anhepatic_phase_time":44,"intraoperative_bleeding":2000,"intubation_time":1.0,"icu_days":8.0,"postop_hospital_days":null,"created_at":"2024-01-01T00:00:00Z","updated_at":"2024-01-01T00:00:00Z"}},
  {"model":"patients.patient","pk":2,"fields":{"patient_id":"201811824","name":"William Perez","sex":1,"age":49.0,"status":"Alive","operation_date":"2018-01-04","hospitalization_number":"1346191","diagnosis_pathological":1,"diagnosis_etiological":3,"diagnosis_coexisting":0,"bmi":24.69,"meld_score":26.8,"child_pugh_score":12,"child_pugh_category":"C","cold_ischemia_time":680,"warm_ischemia_time":5,"operative_time":550,"anhepatic_phase_time":38,"intraoperative_bleeding":1500,"intubation_time":1.0,"icu_days":4.0,"postop_hospital_days":null,"created_at":"2024-01-01T00:00:00Z","updated_at":"2024-01-01T00:00:00Z"}},
  {"model":"patients.patient","pk":3,"fields":{"patient_id":"201810409","name":"Jacob Clark","sex":1,"age":51.0,"status":"Alive","operation_date":"2018-01-11","hospitalization_number":"1347037","diagnosis_pathological":1,"diagnosis_etiological":3,"diagnosis_coexisting":4,"bmi":23.41,"meld_score":11.1,"child_pugh_score":6,"child_pugh_category":"A","cold_ischemia_time":325,"warm_ischemia_time":5,"operative_time":530,"anhepatic_phase_time":52,"intraoperative_bleeding":3000,"intubation_time":1.0,"icu_days":4.0,"postop_hospital_days":null,"created_at":"2024-01-01T00:00:00Z","updated_at":"2024-01-01T00:00:00Z"}},
  {"model":"patients.patient","pk":4,"fields":{"patient_id":"201814741","name":"Timothy Flores","sex":1,"age":58.0,"status":"Alive","operation_date":"2018-01-17","hospitalization_number":"1028130","diagnosis_pathological":1,"diagnosis_etiological":6,"diagnosis_coexisting":0,"bmi":35.0,"meld_score":5.0,"child_pugh_score":8,"child_pugh_category":"B","cold_ischemia_time":299,"warm_ischemia_time":5,"operative_time":650,"anhepatic_phase_time":66,"intraoperative_bleeding":3000,"intubation_time":1.0,"icu_days":9.0,"postop_hospital_days":null,"created_at":"2024-01-01T00:00:00Z","updated_at":"2024-01-01T00:00:00Z"}},
  {"model":"patients.patient","pk":5,"fields":{"patient_id":"201811307","name":"Daniel Garcia","sex":1,"age":43.0,"status":"Alive","operation_date":"2018-01-19","hospitalization_number":"1349925","diagnosis_pathological":1,"diagnosis_etiological":7,"diagnosis_coexisting":0,"bmi":23.32,"meld_score":10.0,"child_pugh_score":10,"child_pugh_category":"C","cold_ischemia_time":492,"warm_ischemia_time":6,"operative_time":515,"anhepatic_phase_time":51,"intraoperative_bleeding":3000,"intubation_time":2.0,"icu_days":46.0,"postop_hospital_days":null,"created_at":"2024-01-01T00:00:00Z","updated_at":"2024-01-01T00:00:00Z"}},
  {"model":"patients.patient","pk":6,"fields":{"patient_id":"201821654","name":"Amanda Martin","sex":2,"age":63.0,"status":"Alive","operation_date":"2018-01-23","hospitalization_number":"1339560","diagnosis_pathological":1,"diagnosis_etiological":1,"diagnosis_coexisting":0,"bmi":22.04,"meld_score":5.0,"child_pugh_score":7,"child_pugh_category":"B","cold_ischemia_time":333,"warm_ischemia_time":0,"operative_time":600,"anhepatic_phase_time":55,"intraoperative_bleeding":1500,"intubation_time":1.0,"icu_days":2.0,"postop_hospital_days":null,"created_at":"2024-01-01T00:00:00Z","updated_at":"2024-01-01T00:00:00Z"}},
  {"model":"patients.patient","pk":7,"fields":{"patient_id":"201816227","name":"David Johnson","sex":1,"age":61.0,"status":"Alive","operation_date":"2018-01-24","hospitalization_number":"1325867","diagnosis_pathological":1,"diagnosis_etiological":3,"diagnosis_coexisting":5,"bmi":22.77,"meld_score":2.1,"child_pugh_score":5,"child_pugh_category":"A","cold_ischemia_time":797,"warm_ischemia_time":5,"operative_time":515,"anhepatic_phase_time":62,"intraoperative_bleeding":800,"intubation_time":1.0,"icu_days":3.0,"postop_hospital_days":null,"created_at":"2024-01-01T00:00:00Z","updated_at":"2024-01-01T00:00:00Z"}},
  {"model":"patients.patient","pk":8,"fields":{"patient_id":"201824012","name":"Sarah Hernandez","sex":2,"age":44.0,"status":"Alive","operation_date":"2018-01-29","hospitalization_number":"1347105","diagnosis_pathological":1,"diagnosis_etiological":3,"diagnosis_coexisting":13,"bmi":18.49,"meld_score":2.7,"child_pugh_score":6,"child_pugh_category":"A","cold_ischemia_time":455,"warm_ischemia_time":0,"operative_time":420,"anhepatic_phase_time":54,"intraoperative_bleeding":600,"intubation_time":1.0,"icu_days":3.0,"postop_hospital_days":null,"created_at":"2024-01-01T00:00:00Z","updated_at":"2024-01-01T00:00:00Z"}},
  {"model":"patients.patient","pk":9,"fields":{"patient_id":"201814554","name":"Michael Thomas","sex":1,"age":56.0,"status":"Alive","operation_date":"2018-01-30","hospitalization_number":"1350923","diagnosis_pathological":1,"diagnosis_etiological":19,"diagnosis_coexisting":4,"bmi":26.89,"meld_score":3.8,"child_pugh_score":7,"child_pugh_category":"B","cold_ischemia_time":542,"warm_ischemia_time":5,"operative_time":755,"anhepatic_phase_time":49,"intraoperative_bleeding":6500,"intubation_time":1.0,"icu_days":7.0,"postop_hospital_days":null,"created_at":"2024-01-01T00:00:00Z","updated_at":"2024-01-01T00:00:00Z"}},
  {"model":"patients.patient","pk":10,"fields":{"patient_id":"201823582","name":"Sarah Jones","sex":2,"age":34.0,"status":"Alive","operation_date":"2018-05-01","hospitalization_number":"1380467","diagnosis_pathological":3,"diagnosis_etiological":3,"diagnosis_coexisting":0,"bmi":24.03,"meld_score":38.0,"child_pugh_score":13,"child_pugh_category":"C","cold_ischemia_time":420,"warm_ischemia_time":0,"operative_time":400,"anhepatic_phase_time":34,"intraoperative_bleeding":4000,"intubation_time":3.0,"icu_days":5.0,"postop_hospital_days":null,"created_at":"2024-01-01T00:00:00Z","updated_at":"2024-01-01T00:00:00Z"}},
  {"model":"patients.patient","pk":11,"fields":{"patient_id":"201819195","name":"John Taylor","sex":1,"age":25.0,"status":"Alive","operation_date":"2018-05-18","hospitalization_number":"984018","diagnosis_pathological":1,"diagnosis_etiological":8,"diagnosis_coexisting":0,"bmi":31.17,"meld_score":1.3,"child_pugh_score":7,"child_pugh_category":"B","cold_ischemia_time":300,"warm_ischemia_time":5,"operative_time":495,"anhepatic_phase_time":65,"intraoperative_bleeding":2500,"intubation_time":2.0,"icu_days":14.0,"postop_hospital_days":null,"created_at":"2024-01-01T00:00:00Z","updated_at":"2024-01-01T00:00:00Z"}},
  {"model":"patients.patient","pk":12,"fields":{"patient_id":"201819125","name":"Jacob Robinson","sex":1,"age":75.0,"status":"Alive","operation_date":"2018-06-30","hospitalization_number":"692347","diagnosis_pathological":1,"diagnosis_etiological":5,"diagnosis_coexisting":5,"bmi":26.35,"meld_score":12.0,"child_pugh_score":9,"child_pugh_category":"B","cold_ischemia_time":337,"warm_ischemia_time":0,"operative_time":470,"anhepatic_phase_time":78,"intraoperative_bleeding":2000,"intubation_time":1.0,"icu_days":60.0,"postop_hospital_days":null,"created_at":"2024-01-01T00:00:00Z","updated_at":"2024-01-01T00:00:00Z"}},
  {"model":"patients.patient","pk":13,"fields":{"patient_id":"201815574","name":"James King","sex":1,"age":54.0,"status":"Alive","operation_date":"2018-08-30","hospitalization_number":"1417534","diagnosis_pathological":17,"diagnosis_etiological":4,"diagnosis_coexisting":0,"bmi":24.22,"meld_score":31.0,"child_pugh_score":13,"child_pugh_category":"C","cold_ischemia_time":360,"warm_ischemia_time":5,"operative_time":845,"anhepatic_phase_time":112,"intraoperative_bleeding":7000,"intubation_time":3.0,"icu_days":8.0,"postop_hospital_days":null,"created_at":"2024-01-01T00:00:00Z","updated_at":"2024-01-01T00:00:00Z"}},
  {"model":"patients.patient","pk":14,"fields":{"patient_id":"201929771","name":"Margaret Perez","sex":2,"age":53.0,"status":"Alive","operation_date":"2019-01-08","hospitalization_number":"1462213","diagnosis_pathological":1,"diagnosis_etiological":8,"diagnosis_coexisting":0,"bmi":23.88,"meld_score":28.1,"child_pugh_score":13,"child_pugh_category":"C","cold_ischemia_time":331,"warm_ischemia_time":5,"operative_time":645,"anhepatic_phase_time":71,"intraoperative_bleeding":600,"intubation_time":1.0,"icu_days":9.0,"postop_hospital_days":null,"created_at":"2024-01-01T00:00:00Z","updated_at":"2024-01-01T00:00:00Z"}},
  {"model":"patients.patient","pk":15,"fields":{"patient_id":"202114462","name":"Nicholas Wright","sex":1,"age":33.0,"status":"Alive","operation_date":"2021-01-02","hospitalization_number":"1689597","diagnosis_pathological":28,"diagnosis_etiological":3,"diagnosis_coexisting":0,"bmi":17.71,"meld_score":15.36,"child_pugh_score":10,"child_pugh_category":"C","cold_ischemia_time":249,"warm_ischemia_time":5,"operative_time":460,"anhepatic_phase_time":48,"intraoperative_bleeding":1500,"intubation_time":1.0,"icu_days":4.79,"postop_hospital_days":null,"created_at":"2024-01-01T00:00:00Z","updated_at":"2024-01-01T00:00:00Z"}},
  {"model":"patients.patient","pk":16,"fields":{"patient_id":"202112546","name":"Nicholas Perez","sex":1,"age":66.0,"status":"Dead","operation_date":"2021-01-04","hospitalization_number":"1699301","diagnosis_pathological":28,"diagnosis_etiological":3,"diagnosis_coexisting":10,"bmi":24.38,"meld_score":6.69,"child_pugh_score":6,"child_pugh_category":"A","cold_ischemia_time":265,"warm_ischemia_time":5,"operative_time":605,"anhepatic_phase_time":65,"intraoperative_bleeding":3000,"intubation_time":1.0,"icu_days":null,"postop_hospital_days":null,"created_at":"2024-01-01T00:00:00Z","updated_at":"2024-01-01T00:00:00Z"}},
  {"model":"patients.patient","pk":17,"fields":{"patient_id":"202214616","name":"Anthony Lee","sex":1,"age":50.0,"status":"Alive","operation_date":"2022-01-05","hospitalization_number":"1828437","diagnosis_pathological":1,"diagnosis_etiological":6,"diagnosis_coexisting":0,"bmi":25.95,"meld_score":15.0,"child_pugh_score":9,"child_pugh_category":"B","cold_ischemia_time":217,"warm_ischemia_time":5,"operative_time":460,"anhepatic_phase_time":50,"intraoperative_bleeding":500,"intubation_time":15.0,"icu_days":72.0,"postop_hospital_days":null,"created_at":"2024-01-01T00:00:00Z","updated_at":"2024-01-01T00:00:00Z"}},
  {"model":"patients.patient","pk":18,"fields":{"patient_id":"202218004","name":"Eric Johnson","sex":1,"age":36.0,"status":"Alive","operation_date":"2022-02-04","hospitalization_number":"1838475","diagnosis_pathological":28,"diagnosis_etiological":3,"diagnosis_coexisting":0,"bmi":27.72,"meld_score":37.0,"child_pugh_score":11,"child_pugh_category":"C","cold_ischemia_time":221,"warm_ischemia_time":5,"operative_time":520,"anhepatic_phase_time":43,"intraoperative_bleeding":1500,"intubation_time":221.0,"icu_days":232.0,"postop_hospital_days":null,"created_at":"2024-01-01T00:00:00Z","updated_at":"2024-01-01T00:00:00Z"}},
  {"model":"patients.patient","pk":19,"fields":{"patient_id":"202229052","name":"Mary Sanchez","sex":2,"age":3.0,"status":"Alive","operation_date":"2022-05-27","hospitalization_number":"1869147","diagnosis_pathological":24,"diagnosis_etiological":19,"diagnosis_coexisting":0,"bmi":17.92,"meld_score":34.0,"child_pugh_score":10,"child_pugh_category":"C","cold_ischemia_time":206,"warm_ischemia_time":5,"operative_time":420,"anhepatic_phase_time":29,"intraoperative_bleeding":200,"intubation_time":407.0,"icu_days":853.0,"postop_hospital_days":null,"created_at":"2024-01-01T00:00:00Z","updated_at":"2024-01-01T00:00:00Z"}},
  {"model":"patients.patient","pk":20,"fields":{"patient_id":"202225050","name":"Stephanie Anderson","sex":2,"age":72.0,"status":"Alive","operation_date":"2022-06-14","hospitalization_number":"1883585","diagnosis_pathological":1,"diagnosis_etiological":1,"diagnosis_coexisting":0,"bmi":26.83,"meld_score":15.0,"child_pugh_score":8,"child_pugh_category":"B","cold_ischemia_time":327,"warm_ischemia_time":0,"operative_time":540,"anhepatic_phase_time":35,"intraoperative_bleeding":500,"intubation_time":80.0,"icu_days":300.0,"postop_hospital_days":null,"created_at":"2024-01-01T00:00:00Z","updated_at":"2024-01-01T00:00:00Z"}}
]
